hi.py
CI_CD_dummy-0.1.0.dist-info/METADATA
CI_CD_dummy-0.1.0.dist-info/WHEEL
CI_CD_dummy-0.1.0.dist-info/top_level.txt
CI_CD_dummy-0.1.0.dist-info/RECORD
