Metadata-Version: 2.1
Name: CI-CD_dummy
Version: 0.1.0
Summary: Dummy CI/CD Pipeline
Requires-Python: >=3.8
